vfm_tool/LSTMmodel.py
vfm_tool/Pandas_data.py
vfm_tool/Spark_data.py
vfm_tool/Utils.py
vfm_tool/__init__.py
vfm_tool/q_control.py
vfm_tool/visualization.py
vfm_tool-1.131.dist-info/METADATA
vfm_tool-1.131.dist-info/WHEEL
vfm_tool-1.131.dist-info/top_level.txt
vfm_tool-1.131.dist-info/RECORD
