Metadata-Version: 2.1
Name: vfm-tool
Version: 1.131
Summary: Individual MSc Project
Home-page: https://github.com/acse-2019/irp-acse-nt719/tree/master/Code/
Author: Nicolas Trinephi
Author-email: nicolas.trinephi@imperial.ac.uk
License: MIT
Platform: UNKNOWN
